{
  "2024-3-3": [
    [
      "2024-03-03 01:41PM",
      "Penn women\u2019s basketball secures spot in Ivy Madness with win over Harvard"
    ]
  ],
  "2024-3-4": [
    [
      "2024-03-04 03:02PM",
      "Penn women\u2019s basketball secures spot in Ivy Madness with win over Harvard"
    ]
  ],
  "2024-3-5": [
    [
      "2024-03-05 03:02PM",
      "Penn women\u2019s basketball secures spot in Ivy Madness with win over Harvard"
    ]
  ],
  "2024-3-6": [
    [
      "2024-03-06 03:02PM",
      "Penn men's squash wins first national championship with victory at Potter Cup"
    ]
  ],
  "2024-3-7": [
    [
      "2024-03-07 03:02PM",
      "Penn extends test-optional policy for Class of 2029 while some Ivies reinstate testing requirement"
    ]
  ],
  "2024-3-8": [
    [
      "2024-03-08 03:02PM",
      "Penn extends test-optional policy for Class of 2029 while some Ivies reinstate testing requirement"
    ]
  ],
  "2024-3-9": [
    [
      "2024-03-09 03:02PM",
      "Penn extends test-optional policy for Class of 2029 while some Ivies reinstate testing requirement"
    ]
  ]
}